ipyscript/__init__.py
ipyscript/_frontend.py
ipyscript/_version.py
ipyscript/example.py
ipyscript/labextension/package.json
ipyscript/labextension/static/480.3170e1a04a36fd51d213.js
ipyscript/labextension/static/568.9b819552fc0835dab1b8.js
ipyscript/labextension/static/remoteEntry.41ea59444039c75a7e2e.js
ipyscript/labextension/static/style.js
ipyscript/labextension/static/third-party-licenses.json
ipyscript/nbextension/extension.js
ipyscript/nbextension/index.js
ipyscript/nbextension/index.js.map
ipyscript/tests/__init__.py
ipyscript/tests/conftest.py
ipyscript/tests/test_example.py
ipyscript/tests/test_nbextension_path.py
ipyscript-0.1.0.dev0.data/data/etc/jupyter/nbconfig/notebook.d/ipyscript.json
ipyscript-0.1.0.dev0.data/data/share/jupyter/labextensions/@datalayer/ipyscript/install.json
ipyscript-0.1.0.dev0.data/data/share/jupyter/labextensions/@datalayer/ipyscript/package.json
ipyscript-0.1.0.dev0.data/data/share/jupyter/labextensions/@datalayer/ipyscript/static/480.3170e1a04a36fd51d213.js
ipyscript-0.1.0.dev0.data/data/share/jupyter/labextensions/@datalayer/ipyscript/static/568.9b819552fc0835dab1b8.js
ipyscript-0.1.0.dev0.data/data/share/jupyter/labextensions/@datalayer/ipyscript/static/remoteEntry.41ea59444039c75a7e2e.js
ipyscript-0.1.0.dev0.data/data/share/jupyter/labextensions/@datalayer/ipyscript/static/style.js
ipyscript-0.1.0.dev0.data/data/share/jupyter/labextensions/@datalayer/ipyscript/static/third-party-licenses.json
ipyscript-0.1.0.dev0.data/data/share/jupyter/nbextensions/ipyscript/extension.js
ipyscript-0.1.0.dev0.data/data/share/jupyter/nbextensions/ipyscript/index.js
ipyscript-0.1.0.dev0.data/data/share/jupyter/nbextensions/ipyscript/index.js.map
ipyscript-0.1.0.dev0.dist-info/LICENSE.txt
ipyscript-0.1.0.dev0.dist-info/METADATA
ipyscript-0.1.0.dev0.dist-info/WHEEL
ipyscript-0.1.0.dev0.dist-info/top_level.txt
ipyscript-0.1.0.dev0.dist-info/RECORD
